NDBC/NDBC.py
NDBC/__init__.py
NDBC/models.py
NDBC/repository/orm.py
NDBC-1.2.0.dist-info/LICENSE.txt
NDBC-1.2.0.dist-info/METADATA
NDBC-1.2.0.dist-info/WHEEL
NDBC-1.2.0.dist-info/top_level.txt
NDBC-1.2.0.dist-info/RECORD
