Metadata-Version: 2.1
Name: NDBC
Version: 1.2.0
Summary: A pacakge to simplify to retrieval and parsing of NOAA NDBC data.
Home-page: https://github.com/supermanzer/NDBC
Author: Ryan Manzer
Author-email: ryan@gensci.org
License: MIT
Project-URL: Documentation, https://supermanzer.github.io/NDBC/html/index.html
Project-URL: Source, https://github.com/supermanzer/NDBC
Project-URL: Changelog, https://supermanzer.github.io/NDBC/html/changelog.html
Project-URL: Tracker, https://github.com/supermanzer/NDBC/issues
Project-URL: Notes, https://supermanzer.github.io/MyNotes/notes/6fc953db-7d86-483d-82c4-40e1675f6d1f/
Platform: any
Classifier: Development Status :: 4 - Beta
Classifier: Programming Language :: Python
License-File: LICENSE.txt
Requires-Dist: pandas (>=1.2.3)
Requires-Dist: requests (>=2.22.0)
Requires-Dist: numpy (>=1.22.0)
Requires-Dist: deprecation (>=2.1.0)
Requires-Dist: beautifulsoup4 (>=4.9.3)
Requires-Dist: bs4 (>=0.0.1)
Requires-Dist: importlib-metadata ; python_version < "3.8"
Provides-Extra: testing
Requires-Dist: setuptools ; extra == 'testing'
Requires-Dist: pytest ; extra == 'testing'
Requires-Dist: pytest-cov ; extra == 'testing'
